{
  "countries": [
    {
      "name": "Afghanistan",
      "code_n3": "004",
      "code_a2": "AF",
      "code_a3": "AFG"
    },
    {
      "name": "Aland Islands",
      "code_n3": "248",
      "code_a2": "AX",
      "code_a3": "ALA"
    },
    {
      "name": "Albania",
      "code_n3": "008",
      "code_a2": "AL",
      "code_a3": "ALB"
    },
    {
      "name": "Algeria",
      "code_n3": "012",
      "code_a2": "DZ",
      "code_a3": "DZA"
    },
    {
      "name": "American Samoa",
      "code_n3": "016",
      "code_a2": "AS",
      "code_a3": "ASM"
    },
    {
      "name": "Andorra",
      "code_n3": "020",
      "code_a2": "AD",
      "code_a3": "AND"
    },
    {
      "name": "Angola",
      "code_n3": "024",
      "code_a2": "AO",
      "code_a3": "AGO"
    },
    {
      "name": "Anguilla",
      "code_n3": "660",
      "code_a2": "AI",
      "code_a3": "AIA"
    },
    {
      "name": "Antarctica",
      "code_n3": "010",
      "code_a2": "AQ",
      "code_a3": "ATA"
    },
    {
      "name": "Antigua and Barbuda",
      "code_n3": "028",
      "code_a2": "AG",
      "code_a3": "ATG"
    },
    {
      "name": "Argentina",
      "code_n3": "032",
      "code_a2": "AR",
      "code_a3": "ARG"
    },
    {
      "name": "Armenia",
      "code_n3": "051",
      "code_a2": "AM",
      "code_a3": "ARM"
    },
    {
      "name": "Aruba",
      "code_n3": "533",
      "code_a2": "AW",
      "code_a3": "ABW"
    },
    {
      "name": "Australia",
      "code_n3": "036",
      "code_a2": "AU",
      "code_a3": "AUS"
    },
    {
      "name": "Austria",
      "code_n3": "040",
      "code_a2": "AT",
      "code_a3": "AUT"
    },
    {
      "name": "Azerbaijan",
      "code_n3": "031",
      "code_a2": "AZ",
      "code_a3": "AZE"
    },
    {
      "name": "Bahamas",
      "code_n3": "044",
      "code_a2": "BS",
      "code_a3": "BHS"
    },
    {
      "name": "Bahrain",
      "code_n3": "048",
      "code_a2": "BH",
      "code_a3": "BHR"
    },
    {
      "name": "Bangladesh",
      "code_n3": "050",
      "code_a2": "BD",
      "code_a3": "BGD"
    },
    {
      "name": "Barbados",
      "code_n3": "052",
      "code_a2": "BB",
      "code_a3": "BRB"
    },
    {
      "name": "Belarus",
      "code_n3": "112",
      "code_a2": "BY",
      "code_a3": "BLR"
    },
    {
      "name": "Belgium",
      "code_n3": "056",
      "code_a2": "BE",
      "code_a3": "BEL"
    },
    {
      "name": "Belize",
      "code_n3": "084",
      "code_a2": "BZ",
      "code_a3": "BLZ"
    },
    {
      "name": "Benin",
      "code_n3": "204",
      "code_a2": "BJ",
      "code_a3": "BEN"
    },
    {
      "name": "Bermuda",
      "code_n3": "060",
      "code_a2": "BM",
      "code_a3": "BMU"
    },
    {
      "name": "Bhutan",
      "code_n3": "064",
      "code_a2": "BT",
      "code_a3": "BTN"
    },
    {
      "name": "Bolivia (Plurinational State of)",
      "code_n3": "068",
      "code_a2": "BO",
      "code_a3": "BOL"
    },
    {
      "name": "Bonaire, Sint Eustatius and Saba",
      "code_n3": "535",
      "code_a2": "BQ",
      "code_a3": "BES"
    },
    {
      "name": "Bosnia and Herzegovina",
      "code_n3": "070",
      "code_a2": "BA",
      "code_a3": "BIH"
    },
    {
      "name": "Botswana",
      "code_n3": "072",
      "code_a2": "BW",
      "code_a3": "BWA"
    },
    {
      "name": "Bouvet Island",
      "code_n3": "074",
      "code_a2": "BV",
      "code_a3": "BVT"
    },
    {
      "name": "Brazil",
      "code_n3": "076",
      "code_a2": "BR",
      "code_a3": "BRA"
    },
    {
      "name": "British Indian Ocean Territory",
      "code_n3": "086",
      "code_a2": "IO",
      "code_a3": "IOT"
    },
    {
      "name": "Brunei Darussalam",
      "code_n3": "096",
      "code_a2": "BN",
      "code_a3": "BRN"
    },
    {
      "name": "Bulgaria",
      "code_n3": "100",
      "code_a2": "BG",
      "code_a3": "BGR"
    },
    {
      "name": "Burkina Faso",
      "code_n3": "854",
      "code_a2": "BF",
      "code_a3": "BFA"
    },
    {
      "name": "Burundi",
      "code_n3": "108",
      "code_a2": "BI",
      "code_a3": "BDI"
    },
    {
      "name": "Cabo Verde",
      "code_n3": "132",
      "code_a2": "CV",
      "code_a3": "CPV"
    },
    {
      "name": "Cambodia",
      "code_n3": "116",
      "code_a2": "KH",
      "code_a3": "KHM"
    },
    {
      "name": "Cameroon",
      "code_n3": "120",
      "code_a2": "CM",
      "code_a3": "CMR"
    },
    {
      "name": "Canada",
      "code_n3": "124",
      "code_a2": "CA",
      "code_a3": "CAN"
    },
    {
      "name": "Cayman Islands",
      "code_n3": "136",
      "code_a2": "KY",
      "code_a3": "CYM"
    },
    {
      "name": "Central African Republic",
      "code_n3": "140",
      "code_a2": "CF",
      "code_a3": "CAF"
    },
    {
      "name": "Chad",
      "code_n3": "148",
      "code_a2": "TD",
      "code_a3": "TCD"
    },
    {
      "name": "Chile",
      "code_n3": "152",
      "code_a2": "CL",
      "code_a3": "CHL"
    },
    {
      "name": "China",
      "code_n3": "156",
      "code_a2": "CN",
      "code_a3": "CHN"
    },
    {
      "name": "Christmas Island",
      "code_n3": "162",
      "code_a2": "CX",
      "code_a3": "CXR"
    },
    {
      "name": "Cocos (Keeling) Islands",
      "code_n3": "166",
      "code_a2": "CC",
      "code_a3": "CCK"
    },
    {
      "name": "Colombia",
      "code_n3": "170",
      "code_a2": "CO",
      "code_a3": "COL"
    },
    {
      "name": "Comoros",
      "code_n3": "174",
      "code_a2": "KM",
      "code_a3": "COM"
    },
    {
      "name": "Congo",
      "code_n3": "178",
      "code_a2": "CG",
      "code_a3": "COG"
    },
    {
      "name": "Congo, Democratic Republic of the",
      "code_n3": "180",
      "code_a2": "CD",
      "code_a3": "COD"
    },
    {
      "name": "Cook Islands",
      "code_n3": "184",
      "code_a2": "CK",
      "code_a3": "COK"
    },
    {
      "name": "Costa Rica",
      "code_n3": "188",
      "code_a2": "CR",
      "code_a3": "CRI"
    },
    {
      "name": "Cote dIvoire",
      "code_n3": "384",
      "code_a2": "CI",
      "code_a3": "CIV"
    },
    {
      "name": "Croatia",
      "code_n3": "191",
      "code_a2": "HR",
      "code_a3": "HRV"
    },
    {
      "name": "Cuba",
      "code_n3": "192",
      "code_a2": "CU",
      "code_a3": "CUB"
    },
    {
      "name": "Curacao",
      "code_n3": "531",
      "code_a2": "CW",
      "code_a3": "CUW"
    },
    {
      "name": "Cyprus",
      "code_n3": "196",
      "code_a2": "CY",
      "code_a3": "CYP"
    },
    {
      "name": "Czechia",
      "code_n3": "203",
      "code_a2": "CZ",
      "code_a3": "CZE"
    },
    {
      "name": "Denmark",
      "code_n3": "208",
      "code_a2": "DK",
      "code_a3": "DNK"
    },
    {
      "name": "Djibouti",
      "code_n3": "262",
      "code_a2": "DJ",
      "code_a3": "DJI"
    },
    {
      "name": "Dominica",
      "code_n3": "212",
      "code_a2": "DM",
      "code_a3": "DMA"
    },
    {
      "name": "Dominican Republic",
      "code_n3": "214",
      "code_a2": "DO",
      "code_a3": "DOM"
    },
    {
      "name": "Ecuador",
      "code_n3": "218",
      "code_a2": "EC",
      "code_a3": "ECU"
    },
    {
      "name": "Egypt",
      "code_n3": "818",
      "code_a2": "EG",
      "code_a3": "EGY"
    },
    {
      "name": "El Salvador",
      "code_n3": "222",
      "code_a2": "SV",
      "code_a3": "SLV"
    },
    {
      "name": "Equatorial Guinea",
      "code_n3": "226",
      "code_a2": "GQ",
      "code_a3": "GNQ"
    },
    {
      "name": "Eritrea",
      "code_n3": "232",
      "code_a2": "ER",
      "code_a3": "ERI"
    },
    {
      "name": "Estonia",
      "code_n3": "233",
      "code_a2": "EE",
      "code_a3": "EST"
    },
    {
      "name": "Eswatini",
      "code_n3": "748",
      "code_a2": "SZ",
      "code_a3": "SWZ"
    },
    {
      "name": "Ethiopia",
      "code_n3": "231",
      "code_a2": "ET",
      "code_a3": "ETH"
    },
    {
      "name": "Falkland Islands (Malvinas)",
      "code_n3": "238",
      "code_a2": "FK",
      "code_a3": "FLK"
    },
    {
      "name": "Faroe Islands",
      "code_n3": "234",
      "code_a2": "FO",
      "code_a3": "FRO"
    },
    {
      "name": "Fiji",
      "code_n3": "242",
      "code_a2": "FJ",
      "code_a3": "FJI"
    },
    {
      "name": "Finland",
      "code_n3": "246",
      "code_a2": "FI",
      "code_a3": "FIN"
    },
    {
      "name": "France",
      "code_n3": "250",
      "code_a2": "FR",
      "code_a3": "FRA"
    },
    {
      "name": "French Guiana",
      "code_n3": "254",
      "code_a2": "GF",
      "code_a3": "GUF"
    },
    {
      "name": "French Polynesia",
      "code_n3": "258",
      "code_a2": "PF",
      "code_a3": "PYF"
    },
    {
      "name": "French Southern Territories",
      "code_n3": "260",
      "code_a2": "TF",
      "code_a3": "ATF"
    },
    {
      "name": "Gabon",
      "code_n3": "266",
      "code_a2": "GA",
      "code_a3": "GAB"
    },
    {
      "name": "Gambia",
      "code_n3": "270",
      "code_a2": "GM",
      "code_a3": "GMB"
    },
    {
      "name": "Georgia",
      "code_n3": "268",
      "code_a2": "GE",
      "code_a3": "GEO"
    },
    {
      "name": "Germany",
      "code_n3": "276",
      "code_a2": "DE",
      "code_a3": "DEU"
    },
    {
      "name": "Ghana",
      "code_n3": "288",
      "code_a2": "GH",
      "code_a3": "GHA"
    },
    {
      "name": "Gibraltar",
      "code_n3": "292",
      "code_a2": "GI",
      "code_a3": "GIB"
    },
    {
      "name": "Greece",
      "code_n3": "300",
      "code_a2": "GR",
      "code_a3": "GRC"
    },
    {
      "name": "Greenland",
      "code_n3": "304",
      "code_a2": "GL",
      "code_a3": "GRL"
    },
    {
      "name": "Grenada",
      "code_n3": "308",
      "code_a2": "GD",
      "code_a3": "GRD"
    },
    {
      "name": "Guadeloupe",
      "code_n3": "312",
      "code_a2": "GP",
      "code_a3": "GLP"
    },
    {
      "name": "Guam",
      "code_n3": "316",
      "code_a2": "GU",
      "code_a3": "GUM"
    },
    {
      "name": "Guatemala",
      "code_n3": "320",
      "code_a2": "GT",
      "code_a3": "GTM"
    },
    {
      "name": "Guernsey",
      "code_n3": "831",
      "code_a2": "GG",
      "code_a3": "GGY"
    },
    {
      "name": "Guinea",
      "code_n3": "324",
      "code_a2": "GN",
      "code_a3": "GIN"
    },
    {
      "name": "Guinea-Bissau",
      "code_n3": "624",
      "code_a2": "GW",
      "code_a3": "GNB"
    },
    {
      "name": "Guyana",
      "code_n3": "328",
      "code_a2": "GY",
      "code_a3": "GUY"
    },
    {
      "name": "Haiti",
      "code_n3": "332",
      "code_a2": "HT",
      "code_a3": "HTI"
    },
    {
      "name": "Heard Island and McDonald Islands",
      "code_n3": "334",
      "code_a2": "HM",
      "code_a3": "HMD"
    },
    {
      "name": "Holy See",
      "code_n3": "336",
      "code_a2": "VA",
      "code_a3": "VAT"
    },
    {
      "name": "Honduras",
      "code_n3": "340",
      "code_a2": "HN",
      "code_a3": "HND"
    },
    {
      "name": "Hong Kong",
      "code_n3": "344",
      "code_a2": "HK",
      "code_a3": "HKG"
    },
    {
      "name": "Hungary",
      "code_n3": "348",
      "code_a2": "HU",
      "code_a3": "HUN"
    },
    {
      "name": "Iceland",
      "code_n3": "352",
      "code_a2": "IS",
      "code_a3": "ISL"
    },
    {
      "name": "India",
      "code_n3": "356",
      "code_a2": "IN",
      "code_a3": "IND"
    },
    {
      "name": "Indonesia",
      "code_n3": "360",
      "code_a2": "ID",
      "code_a3": "IDN"
    },
    {
      "name": "Iran (Islamic Republic of)",
      "code_n3": "364",
      "code_a2": "IR",
      "code_a3": "IRN"
    },
    {
      "name": "Iraq",
      "code_n3": "368",
      "code_a2": "IQ",
      "code_a3": "IRQ"
    },
    {
      "name": "Ireland",
      "code_n3": "372",
      "code_a2": "IE",
      "code_a3": "IRL"
    },
    {
      "name": "Isle of Man",
      "code_n3": "833",
      "code_a2": "IM",
      "code_a3": "IMN"
    },
    {
      "name": "Israel",
      "code_n3": "376",
      "code_a2": "IL",
      "code_a3": "ISR"
    },
    {
      "name": "Italy",
      "code_n3": "380",
      "code_a2": "IT",
      "code_a3": "ITA"
    },
    {
      "name": "Jamaica",
      "code_n3": "388",
      "code_a2": "JM",
      "code_a3": "JAM"
    },
    {
      "name": "Japan",
      "code_n3": "392",
      "code_a2": "JP",
      "code_a3": "JPN"
    },
    {
      "name": "Jersey",
      "code_n3": "832",
      "code_a2": "JE",
      "code_a3": "JEY"
    },
    {
      "name": "Jordan",
      "code_n3": "400",
      "code_a2": "JO",
      "code_a3": "JOR"
    },
    {
      "name": "Kazakhstan",
      "code_n3": "398",
      "code_a2": "KZ",
      "code_a3": "KAZ"
    },
    {
      "name": "Kenya",
      "code_n3": "404",
      "code_a2": "KE",
      "code_a3": "KEN"
    },
    {
      "name": "Kiribati",
      "code_n3": "296",
      "code_a2": "KI",
      "code_a3": "KIR"
    },
    {
      "name": "Korea (Democratic Peoples Republic of)",
      "code_n3": "408",
      "code_a2": "KP",
      "code_a3": "PRK"
    },
    {
      "name": "Korea, Republic of",
      "code_n3": "410",
      "code_a2": "KR",
      "code_a3": "KOR"
    },
    {
      "name": "Kuwait",
      "code_n3": "414",
      "code_a2": "KW",
      "code_a3": "KWT"
    },
    {
      "name": "Kyrgyzstan",
      "code_n3": "417",
      "code_a2": "KG",
      "code_a3": "KGZ"
    },
    {
      "name": "Lao Peoples Democratic Republic",
      "code_n3": "418",
      "code_a2": "LA",
      "code_a3": "LAO"
    },
    {
      "name": "Latvia",
      "code_n3": "428",
      "code_a2": "LV",
      "code_a3": "LVA"
    },
    {
      "name": "Lebanon",
      "code_n3": "422",
      "code_a2": "LB",
      "code_a3": "LBN"
    },
    {
      "name": "Lesotho",
      "code_n3": "426",
      "code_a2": "LS",
      "code_a3": "LSO"
    },
    {
      "name": "Liberia",
      "code_n3": "430",
      "code_a2": "LR",
      "code_a3": "LBR"
    },
    {
      "name": "Libya",
      "code_n3": "434",
      "code_a2": "LY",
      "code_a3": "LBY"
    },
    {
      "name": "Liechtenstein",
      "code_n3": "438",
      "code_a2": "LI",
      "code_a3": "LIE"
    },
    {
      "name": "Lithuania",
      "code_n3": "440",
      "code_a2": "LT",
      "code_a3": "LTU"
    },
    {
      "name": "Luxembourg",
      "code_n3": "442",
      "code_a2": "LU",
      "code_a3": "LUX"
    },
    {
      "name": "Macao",
      "code_n3": "446",
      "code_a2": "MO",
      "code_a3": "MAC"
    },
    {
      "name": "Madagascar",
      "code_n3": "450",
      "code_a2": "MG",
      "code_a3": "MDG"
    },
    {
      "name": "Malawi",
      "code_n3": "454",
      "code_a2": "MW",
      "code_a3": "MWI"
    },
    {
      "name": "Malaysia",
      "code_n3": "458",
      "code_a2": "MY",
      "code_a3": "MYS"
    },
    {
      "name": "Maldives",
      "code_n3": "462",
      "code_a2": "MV",
      "code_a3": "MDV"
    },
    {
      "name": "Mali",
      "code_n3": "466",
      "code_a2": "ML",
      "code_a3": "MLI"
    },
    {
      "name": "Malta",
      "code_n3": "470",
      "code_a2": "MT",
      "code_a3": "MLT"
    },
    {
      "name": "Marshall Islands",
      "code_n3": "584",
      "code_a2": "MH",
      "code_a3": "MHL"
    },
    {
      "name": "Martinique",
      "code_n3": "474",
      "code_a2": "MQ",
      "code_a3": "MTQ"
    },
    {
      "name": "Mauritania",
      "code_n3": "478",
      "code_a2": "MR",
      "code_a3": "MRT"
    },
    {
      "name": "Mauritius",
      "code_n3": "480",
      "code_a2": "MU",
      "code_a3": "MUS"
    },
    {
      "name": "Mayotte",
      "code_n3": "175",
      "code_a2": "YT",
      "code_a3": "MYT"
    },
    {
      "name": "Mexico",
      "code_n3": "484",
      "code_a2": "MX",
      "code_a3": "MEX"
    },
    {
      "name": "Micronesia (Federated States of)",
      "code_n3": "583",
      "code_a2": "FM",
      "code_a3": "FSM"
    },
    {
      "name": "Moldova, Republic of",
      "code_n3": "498",
      "code_a2": "MD",
      "code_a3": "MDA"
    },
    {
      "name": "Monaco",
      "code_n3": "492",
      "code_a2": "MC",
      "code_a3": "MCO"
    },
    {
      "name": "Mongolia",
      "code_n3": "496",
      "code_a2": "MN",
      "code_a3": "MNG"
    },
    {
      "name": "Montenegro",
      "code_n3": "499",
      "code_a2": "ME",
      "code_a3": "MNE"
    },
    {
      "name": "Montserrat",
      "code_n3": "500",
      "code_a2": "MS",
      "code_a3": "MSR"
    },
    {
      "name": "Morocco",
      "code_n3": "504",
      "code_a2": "MA",
      "code_a3": "MAR"
    },
    {
      "name": "Mozambique",
      "code_n3": "508",
      "code_a2": "MZ",
      "code_a3": "MOZ"
    },
    {
      "name": "Myanmar",
      "code_n3": "104",
      "code_a2": "MM",
      "code_a3": "MMR"
    },
    {
      "name": "Namibia",
      "code_n3": "516",
      "code_a2": "NA",
      "code_a3": "NAM"
    },
    {
      "name": "Nauru",
      "code_n3": "520",
      "code_a2": "NR",
      "code_a3": "NRU"
    },
    {
      "name": "Nepal",
      "code_n3": "524",
      "code_a2": "NP",
      "code_a3": "NPL"
    },
    {
      "name": "Netherlands",
      "code_n3": "528",
      "code_a2": "NL",
      "code_a3": "NLD"
    },
    {
      "name": "New Caledonia",
      "code_n3": "540",
      "code_a2": "NC",
      "code_a3": "NCL"
    },
    {
      "name": "New Zealand",
      "code_n3": "554",
      "code_a2": "NZ",
      "code_a3": "NZL"
    },
    {
      "name": "Nicaragua",
      "code_n3": "558",
      "code_a2": "NI",
      "code_a3": "NIC"
    },
    {
      "name": "Niger",
      "code_n3": "562",
      "code_a2": "NE",
      "code_a3": "NER"
    },
    {
      "name": "Nigeria",
      "code_n3": "566",
      "code_a2": "NG",
      "code_a3": "NGA"
    },
    {
      "name": "Niue",
      "code_n3": "570",
      "code_a2": "NU",
      "code_a3": "NIU"
    },
    {
      "name": "Norfolk Island",
      "code_n3": "574",
      "code_a2": "NF",
      "code_a3": "NFK"
    },
    {
      "name": "North Macedonia",
      "code_n3": "807",
      "code_a2": "MK",
      "code_a3": "MKD"
    },
    {
      "name": "Northern Mariana Islands",
      "code_n3": "580",
      "code_a2": "MP",
      "code_a3": "MNP"
    },
    {
      "name": "Norway",
      "code_n3": "578",
      "code_a2": "NO",
      "code_a3": "NOR"
    },
    {
      "name": "Oman",
      "code_n3": "512",
      "code_a2": "OM",
      "code_a3": "OMN"
    },
    {
      "name": "Pakistan",
      "code_n3": "586",
      "code_a2": "PK",
      "code_a3": "PAK"
    },
    {
      "name": "Palau",
      "code_n3": "585",
      "code_a2": "PW",
      "code_a3": "PLW"
    },
    {
      "name": "Palestine, State of",
      "code_n3": "275",
      "code_a2": "PS",
      "code_a3": "PSE"
    },
    {
      "name": "Panama",
      "code_n3": "591",
      "code_a2": "PA",
      "code_a3": "PAN"
    },
    {
      "name": "Papua New Guinea",
      "code_n3": "598",
      "code_a2": "PG",
      "code_a3": "PNG"
    },
    {
      "name": "Paraguay",
      "code_n3": "600",
      "code_a2": "PY",
      "code_a3": "PRY"
    },
    {
      "name": "Peru",
      "code_n3": "604",
      "code_a2": "PE",
      "code_a3": "PER"
    },
    {
      "name": "Philippines",
      "code_n3": "608",
      "code_a2": "PH",
      "code_a3": "PHL"
    },
    {
      "name": "Pitcairn",
      "code_n3": "612",
      "code_a2": "PN",
      "code_a3": "PCN"
    },
    {
      "name": "Poland",
      "code_n3": "616",
      "code_a2": "PL",
      "code_a3": "POL"
    },
    {
      "name": "Portugal",
      "code_n3": "620",
      "code_a2": "PT",
      "code_a3": "PRT"
    },
    {
      "name": "Puerto Rico",
      "code_n3": "630",
      "code_a2": "PR",
      "code_a3": "PRI"
    },
    {
      "name": "Qatar",
      "code_n3": "634",
      "code_a2": "QA",
      "code_a3": "QAT"
    },
    {
      "name": "Reunion",
      "code_n3": "638",
      "code_a2": "RE",
      "code_a3": "REU"
    },
    {
      "name": "Romania",
      "code_n3": "642",
      "code_a2": "RO",
      "code_a3": "ROU"
    },
    {
      "name": "Russian Federation",
      "code_n3": "643",
      "code_a2": "RU",
      "code_a3": "RUS"
    },
    {
      "name": "Rwanda",
      "code_n3": "646",
      "code_a2": "RW",
      "code_a3": "RWA"
    },
    {
      "name": "Saint Barthelemy",
      "code_n3": "652",
      "code_a2": "BL",
      "code_a3": "BLM"
    },
    {
      "name": "Saint Helena, Ascension and Tristan da Cunha",
      "code_n3": "654",
      "code_a2": "SH",
      "code_a3": "SHN"
    },
    {
      "name": "Saint Kitts and Nevis",
      "code_n3": "659",
      "code_a2": "KN",
      "code_a3": "KNA"
    },
    {
      "name": "Saint Lucia",
      "code_n3": "662",
      "code_a2": "LC",
      "code_a3": "LCA"
    },
    {
      "name": "Saint Martin (French part)",
      "code_n3": "663",
      "code_a2": "MF",
      "code_a3": "MAF"
    },
    {
      "name": "Saint Pierre and Miquelon",
      "code_n3": "666",
      "code_a2": "PM",
      "code_a3": "SPM"
    },
    {
      "name": "Saint Vincent and the Grenadines",
      "code_n3": "670",
      "code_a2": "VC",
      "code_a3": "VCT"
    },
    {
      "name": "Samoa",
      "code_n3": "882",
      "code_a2": "WS",
      "code_a3": "WSM"
    },
    {
      "name": "San Marino",
      "code_n3": "674",
      "code_a2": "SM",
      "code_a3": "SMR"
    },
    {
      "name": "Sao Tome and Principe",
      "code_n3": "678",
      "code_a2": "ST",
      "code_a3": "STP"
    },
    {
      "name": "Saudi Arabia",
      "code_n3": "682",
      "code_a2": "SA",
      "code_a3": "SAU"
    },
    {
      "name": "Senegal",
      "code_n3": "686",
      "code_a2": "SN",
      "code_a3": "SEN"
    },
    {
      "name": "Serbia",
      "code_n3": "688",
      "code_a2": "RS",
      "code_a3": "SRB"
    },
    {
      "name": "Seychelles",
      "code_n3": "690",
      "code_a2": "SC",
      "code_a3": "SYC"
    },
    {
      "name": "Sierra Leone",
      "code_n3": "694",
      "code_a2": "SL",
      "code_a3": "SLE"
    },
    {
      "name": "Singapore",
      "code_n3": "702",
      "code_a2": "SG",
      "code_a3": "SGP"
    },
    {
      "name": "Sint Maarten (Dutch part)",
      "code_n3": "534",
      "code_a2": "SX",
      "code_a3": "SXM"
    },
    {
      "name": "Slovakia",
      "code_n3": "703",
      "code_a2": "SK",
      "code_a3": "SVK"
    },
    {
      "name": "Slovenia",
      "code_n3": "705",
      "code_a2": "SI",
      "code_a3": "SVN"
    },
    {
      "name": "Solomon Islands",
      "code_n3": "090",
      "code_a2": "SB",
      "code_a3": "SLB"
    },
    {
      "name": "Somalia",
      "code_n3": "706",
      "code_a2": "SO",
      "code_a3": "SOM"
    },
    {
      "name": "South Africa",
      "code_n3": "710",
      "code_a2": "ZA",
      "code_a3": "ZAF"
    },
    {
      "name": "South Georgia and the South Sandwich Islands",
      "code_n3": "239",
      "code_a2": "GS",
      "code_a3": "SGS"
    },
    {
      "name": "South Sudan",
      "code_n3": "728",
      "code_a2": "SS",
      "code_a3": "SSD"
    },
    {
      "name": "Spain",
      "code_n3": "724",
      "code_a2": "ES",
      "code_a3": "ESP"
    },
    {
      "name": "Sri Lanka",
      "code_n3": "144",
      "code_a2": "LK",
      "code_a3": "LKA"
    },
    {
      "name": "Sudan",
      "code_n3": "729",
      "code_a2": "SD",
      "code_a3": "SDN"
    },
    {
      "name": "Suriname",
      "code_n3": "740",
      "code_a2": "SR",
      "code_a3": "SUR"
    },
    {
      "name": "Svalbard and Jan Mayen",
      "code_n3": "744",
      "code_a2": "SJ",
      "code_a3": "SJM"
    },
    {
      "name": "Sweden",
      "code_n3": "752",
      "code_a2": "SE",
      "code_a3": "SWE"
    },
    {
      "name": "Switzerland",
      "code_n3": "756",
      "code_a2": "CH",
      "code_a3": "CHE"
    },
    {
      "name": "Syrian Arab Republic",
      "code_n3": "760",
      "code_a2": "SY",
      "code_a3": "SYR"
    },
    {
      "name": "Taiwan, Province of China",
      "code_n3": "158",
      "code_a2": "TW",
      "code_a3": "TWN"
    },
    {
      "name": "Tajikistan",
      "code_n3": "762",
      "code_a2": "TJ",
      "code_a3": "TJK"
    },
    {
      "name": "Tanzania, United Republic of",
      "code_n3": "834",
      "code_a2": "TZ",
      "code_a3": "TZA"
    },
    {
      "name": "Thailand",
      "code_n3": "764",
      "code_a2": "TH",
      "code_a3": "THA"
    },
    {
      "name": "Timor-Leste",
      "code_n3": "626",
      "code_a2": "TL",
      "code_a3": "TLS"
    },
    {
      "name": "Togo",
      "code_n3": "768",
      "code_a2": "TG",
      "code_a3": "TGO"
    },
    {
      "name": "Tokelau",
      "code_n3": "772",
      "code_a2": "TK",
      "code_a3": "TKL"
    },
    {
      "name": "Tonga",
      "code_n3": "776",
      "code_a2": "TO",
      "code_a3": "TON"
    },
    {
      "name": "Trinidad and Tobago",
      "code_n3": "780",
      "code_a2": "TT",
      "code_a3": "TTO"
    },
    {
      "name": "Tunisia",
      "code_n3": "788",
      "code_a2": "TN",
      "code_a3": "TUN"
    },
    {
      "name": "Turkey",
      "code_n3": "792",
      "code_a2": "TR",
      "code_a3": "TUR"
    },
    {
      "name": "Turkmenistan",
      "code_n3": "795",
      "code_a2": "TM",
      "code_a3": "TKM"
    },
    {
      "name": "Turks and Caicos Islands",
      "code_n3": "796",
      "code_a2": "TC",
      "code_a3": "TCA"
    },
    {
      "name": "Tuvalu",
      "code_n3": "798",
      "code_a2": "TV",
      "code_a3": "TUV"
    },
    {
      "name": "Uganda",
      "code_n3": "800",
      "code_a2": "UG",
      "code_a3": "UGA"
    },
    {
      "name": "Ukraine",
      "code_n3": "804",
      "code_a2": "UA",
      "code_a3": "UKR"
    },
    {
      "name": "United Arab Emirates",
      "code_n3": "784",
      "code_a2": "AE",
      "code_a3": "ARE"
    },
    {
      "name": "United Kingdom of Great Britain and Northern Ireland",
      "code_n3": "826",
      "code_a2": "GB",
      "code_a3": "GBR"
    },
    {
      "name": "United States of America",
      "code_n3": "840",
      "code_a2": "US",
      "code_a3": "USA"
    },
    {
      "name": "United States Minor Outlying Islands",
      "code_n3": "581",
      "code_a2": "UM",
      "code_a3": "UMI"
    },
    {
      "name": "Uruguay",
      "code_n3": "858",
      "code_a2": "UY",
      "code_a3": "URY"
    },
    {
      "name": "Uzbekistan",
      "code_n3": "860",
      "code_a2": "UZ",
      "code_a3": "UZB"
    },
    {
      "name": "Vanuatu",
      "code_n3": "548",
      "code_a2": "VU",
      "code_a3": "VUT"
    },
    {
      "name": "Venezuela (Bolivarian Republic of)",
      "code_n3": "862",
      "code_a2": "VE",
      "code_a3": "VEN"
    },
    {
      "name": "Viet Nam",
      "code_n3": "704",
      "code_a2": "VN",
      "code_a3": "VNM"
    },
    {
      "name": "Virgin Islands (British)",
      "code_n3": "092",
      "code_a2": "VG",
      "code_a3": "VGB"
    },
    {
      "name": "Virgin Islands (U.S.)",
      "code_n3": "850",
      "code_a2": "VI",
      "code_a3": "VIR"
    },
    {
      "name": "Wallis and Futuna",
      "code_n3": "876",
      "code_a2": "WF",
      "code_a3": "WLF"
    },
    {
      "name": "Western Sahara",
      "code_n3": "732",
      "code_a2": "EH",
      "code_a3": "ESH"
    },
    {
      "name": "Yemen",
      "code_n3": "887",
      "code_a2": "YE",
      "code_a3": "YEM"
    },
    {
      "name": "Zambia",
      "code_n3": "894",
      "code_a2": "ZM",
      "code_a3": "ZMB"
    },
    {
      "name": "Zimbabwe",
      "code_n3": "716",
      "code_a2": "ZW",
      "code_a3": "ZWE"
    }
  ]
}